{
    "name": "Diogo D\u00f3ria",
    "movies": [
        "\u76f4\u5230\u4e16\u754c\u5c3d\u5934 Bis ans Ende der Welt"
    ],
    "male": "\u7537",
    "xingzuo": "\u767d\u7f8a\u5ea7",
    "birth": "1953-04-16",
    "area": "\u8461\u8404\u7259,\u91cc\u65af\u672c",
    "zhiye": [
        "\u6f14\u5458"
    ],
    "moreName": [],
    "family": [],
    "intro": "\n            \u3000\u3000\n    ",
    "hezuo": [
        [
            "\u5415\u8fea\u683c\u00b7\u798f\u683c\u52d2 R\u00fcdiger Vogler",
            1
        ],
        [
            "\u5384\u5c3c\u00b7\u4e01\u6208 Ernie Dingo",
            1
        ],
        [
            "\u8ba9\u5a1c\u00b7\u83ab\u7f57 Jeanne Moreau",
            1
        ],
        [
            "\u5947\u514b\u00b7\u5965\u5c14\u7279\u52a0 Chick Ortega",
            1
        ],
        [
            "\u5a01\u5ec9\u00b7\u8d6b\u7279 William Hurt",
            1
        ],
        [
            "\u57c3\u8fea\u00b7\u7c73\u5207\u5c14 Eddy Mitchell",
            1
        ],
        [
            "\u7d22\u5c14\u7ef4\u683c\u00b7\u591a\u9a6c\u5c14\u5766 Solveig Dommartin",
            1
        ],
        [
            "\u963f\u5fb7\u5c14\u00b7\u5362\u8328 Adelle Lutz",
            1
        ],
        [
            "\u5c71\u59c6\u00b7\u5c3c\u5c14 Sam Neill",
            1
        ],
        [
            "\u8096\u592e Yang Xiao",
            0
        ]
    ]
}