{
    "name": "MacInTalk",
    "movies": [
        "\u673a\u5668\u4eba\u603b\u52a8\u5458 WALL\u00b7E"
    ],
    "male": "not found",
    "xingzuo": "not found",
    "birth": "not found",
    "area": "not found",
    "zhiye": [
        "\u914d\u97f3"
    ],
    "moreName": [],
    "family": [],
    "intro": "\n            \u3000\u3000\n    ",
    "hezuo": [
        [
            "\u9c8d\u4f2f\u00b7\u4f2f\u6839 Bob Bergen",
            1
        ],
        [
            "\u4f5b\u83b1\u5fb7\u00b7\u5a01\u62c9\u7279 Fred Willard",
            1
        ],
        [
            "\u897f\u683c\u59ae\u00b7\u97e6\u5f17 Sigourney Weaver",
            1
        ],
        [
            "\u6cf0\u8fea\u00b7\u725b\u987f Teddy Newton",
            1
        ],
        [
            "\u6770\u592b\u00b7\u683c\u5c14\u6797 Jeff Garlin",
            1
        ],
        [
            "\u51ef\u831c\u00b7\u7eb3\u57fa\u9ea6 Kathy Najimy",
            1
        ],
        [
            "\u672c\u00b7\u8d1d\u5c14\u7279 Ben Burtt",
            1
        ],
        [
            "\u7ea6\u7ff0\u00b7\u62c9\u5c91\u8d1d\u683c John Ratzenberger",
            1
        ],
        [
            "\u827e\u4e3d\u838e\u00b7\u5948\u7279 Elissa Knight",
            1
        ],
        [
            "\u8096\u592e Yang Xiao",
            0
        ]
    ]
}