{
    "name": "\u514b\u91cc\u65af\u00b7\u52d2\u59c6\u5f7b Kris Lemche",
    "movies": [
        "\u6b7b\u795e\u6765\u4e863 Final Destination 3"
    ],
    "male": "\u7537",
    "xingzuo": "\u53cc\u9c7c\u5ea7",
    "birth": "1978-03-20",
    "area": "Brampton, Ontario, Canada",
    "zhiye": [
        "\u6f14\u5458"
    ],
    "moreName": [],
    "family": [
        "Matthew Lemche\uff08\u5f1f\uff09"
    ],
    "intro": "\n\u3000\u3000Lemche was born in Brampton, Ontario to a schoolteacher mother and a father who was the proprietor of a heating business.[1] Lemche attended the Mayfield School of Arts. His brother, Matt Lemche, is also an actor.\u3000\u3000At 17, he answered a newspaper casting call and won a role on the Disney series Flash Forward.\u3000\u3000Abandoning plans to study biochemistry in University, he instead moved to Prince Edward Island to work on the CBC series Emily...(\u5c55\u5f00\u5168\u90e8)\n\u3000\u3000Lemche was born in Brampton, Ontario to a schoolteacher mother and a father who was the proprietor of a heating business.[1] Lemche attended the Mayfield School of Arts. His brother, Matt Lemche, is also an actor.\u3000\u3000At 17, he answered a newspaper casting call and won a role on the Disney series Flash Forward.\u3000\u3000Abandoning plans to study biochemistry in University, he instead moved to Prince Edward Island to work on the CBC series Emily of New Moon. His work on the show earned him a Gemini Award. He traveled to Dublin to film Newton: A Tale of Two Isaacs, Romania for Teen Knight and Prague for Joan of Arc.\u3000\u3000He has appeared on La Femme Nikita and in movies such as eXistenZ, Ginger Snaps and Knockaround Guys. In in the United States, he has appeared on 'Dragnet', was a series regular on My Guide to Becoming a Rock Star, and had a recurring role on Joan of Arcadia as one of the incarnations of God. He was then seen on the big screen in Ginger Snaps, Final Destination 3 and A Simple Curve. He has appeared on the CBS show Criminal Minds in the episode Blood Hungry, and three episodes of Ghost Whisperer. Most recently, he had a major role in the television movie 24: Redemption. Lemche stars also in the Horror film \"Grinder\" who is directed by Richard Clark Jr.\n",
    "hezuo": [
        [
            "\u745e\u6069\u00b7\u83ab\u91cc\u66fc Ryan Merriman",
            1
        ],
        [
            "\u5207\u5170\u00b7\u897f\u8499\u65af Chelan Simmons",
            1
        ],
        [
            "\u739b\u4e3d\u00b7\u4f0a\u4e3d\u838e\u767d\u00b7\u6e29\u65af\u7279\u5fb7 Mary Elizabeth Winstead",
            1
        ],
        [
            "\u514b\u745e\u65af\u5854\u5c14\u00b7\u6d1b\u7ef4 Crystal Lowe",
            1
        ],
        [
            "\u5409\u5a1c\u00b7\u8d6b\u5c14\u987f Gina Holden",
            1
        ],
        [
            "\u8428\u59c6\u00b7\u4f0a\u65af\u987f Sam Easton",
            1
        ],
        [
            "\u6770\u897f\u00b7\u83ab\u65af Jesse Moss",
            1
        ],
        [
            "\u7279\u590f\u65af\u00b7\u5df4\u7279\u5c14 Texas Battle",
            1
        ],
        [
            "\u4e9a\u8389\u514b\u5179\u00b7\u7ea6\u7ff0\u900a Alexz Johnson",
            1
        ],
        [
            "\u8096\u592e Yang Xiao",
            0
        ]
    ]
}