{
    "name": "\u514b\u91cc\u00b7\u7ea6\u7ff0\u900a Corey Johnson",
    "movies": [
        "\u673a\u68b0\u59ec Ex Machina"
    ],
    "male": "\u7537",
    "xingzuo": "\u91d1\u725b\u5ea7",
    "birth": "1961-05-17",
    "area": "\u7f8e\u56fd,\u8def\u6613\u65af\u5b89\u90a3\u5dde,\u65b0\u5965\u5c14\u826f",
    "zhiye": [
        "\u6f14\u5458"
    ],
    "moreName": [],
    "family": [],
    "intro": "\n            \u3000\u3000\n    ",
    "hezuo": [
        [
            "\u6c34\u91ce\u7d22\u8bfa\u5a05 Sonoya Mizuno",
            1
        ],
        [
            "\u827e\u4e3d\u897f\u4e9a\u00b7\u7ef4\u574e\u5fb7 Alicia Vikander",
            1
        ],
        [
            "\u591a\u59c6\u7eb3\u5c14\u00b7\u683c\u91cc\u68ee Domhnall Gleeson",
            1
        ],
        [
            "\u5965\u65af\u5361\u00b7\u4f0a\u8428\u514b Oscar Isaac",
            1
        ],
        [
            "\u8096\u592e Yang Xiao",
            0
        ],
        [
            "\u6770\u514b\u00b7\u6606\u5361 Jake Cuenca",
            0
        ],
        [
            "\u8302\u6587\u00b7\u9053\u683c\u62c9\u65af Melvyn Douglas",
            0
        ],
        [
            "\u5218\u627f\u7766 Yoo Seung-Mok",
            0
        ],
        [
            "\u521d\u4e95\u8a00\u8363 Kotoe Hatsui",
            0
        ],
        [
            "\u4e3d\u5854\u00b7\u79d1\u5c14\u6cf0\u585e Rita Cortese",
            0
        ]
    ]
}