{
    "name": "\u51ef\u8389\u00b7\u6797\u5947 Kelly Lynch",
    "movies": [
        "\u9739\u96f3\u5a07\u5a03 Charlie's Angels"
    ],
    "male": "\u5973",
    "xingzuo": "\u6c34\u74f6\u5ea7",
    "birth": "1959-01-31",
    "area": "\u7f8e\u56fd,\u660e\u5c3c\u82cf\u8fbe\u5dde",
    "zhiye": [
        "\u6f14\u5458"
    ],
    "moreName": [],
    "family": [],
    "intro": "\n            \u3000\u3000\n    ",
    "hezuo": [
        [
            "\u9a6c\u7279\u00b7\u52d2\u5e03\u6717 Matt LeBlanc",
            1
        ],
        [
            "\u6bd4\u5c14\u00b7\u9ed8\u745e Bill Murray",
            1
        ],
        [
            "\u514b\u91cc\u65af\u5e73\u00b7\u683c\u6d1b\u5f17 Crispin Glover",
            1
        ],
        [
            "LL Cool J",
            1
        ],
        [
            "\u5361\u6885\u9686\u00b7\u8fea\u4e9a\u5179 Cameron Diaz",
            1
        ],
        [
            "\u5c71\u59c6\u00b7\u6d1b\u514b\u5a01\u5c14 Sam Rockwell",
            1
        ],
        [
            "\u5218\u7389\u73b2 Lucy Liu",
            1
        ],
        [
            "\u5fb7\u9c81\u00b7\u5df4\u91cc\u6469\u5c14 Drew Barrymore",
            1
        ],
        [
            "\u8482\u59c6\u00b7\u514b\u91cc Tim Curry",
            1
        ],
        [
            "\u8096\u592e Yang Xiao",
            0
        ]
    ]
}