{
    "name": "\u5207\u65af\u62c9\u00b7\u5188\u8428\u96f7\u5179 Chelsea Gonzalez",
    "movies": [
        "\u6b7b\u4ea1\u5360\u535c2\uff1a\u6076\u7075\u59cb\u6e90 Ouija: Origin of Evil"
    ],
    "male": "not found",
    "xingzuo": "not found",
    "birth": "not found",
    "area": "not found",
    "zhiye": [
        "\u6f14\u5458"
    ],
    "moreName": [],
    "family": [],
    "intro": "\n            \u3000\u3000\n    ",
    "hezuo": [
        [
            "\u6797\u80af\u00b7\u6885\u5c14\u5f7b Lincoln Melcher",
            1
        ],
        [
            "\u8fc8\u514b\u5c14\u00b7\u97e6\u5f17 Michael Weaver",
            1
        ],
        [
            "\u9732\u9732\u00b7\u5a01\u5c14\u900a Lulu Wilson",
            1
        ],
        [
            "\u5c3c\u53ef\u62c9\u65af\u00b7\u80af\u5357 Nicholas Keenan",
            1
        ],
        [
            "\u4ea8\u5229\u00b7\u6258\u9a6c\u65af Henry Thomas",
            1
        ],
        [
            "\u5e15\u514b\u00b7\u9a6c\u514b Parker Mack",
            1
        ],
        [
            "\u4f0a\u8389\u838e\u767d\u00b7\u91cc\u745f Elizabeth Reaser",
            1
        ],
        [
            "\u9053\u683c\u00b7\u743c\u65af Doug Jones",
            1
        ],
        [
            "\u5b89\u5a1c\u4e3d\u4e1d\u00b7\u5df4\u7d22 Annalise Basso",
            1
        ],
        [
            "\u8096\u592e Yang Xiao",
            0
        ]
    ]
}