{
    "name": "\u5218\u627f\u7766 Yoo Seung-Mok",
    "movies": [
        "\u6076\u4eba\u4f20 \uc545\uc778\uc804",
        "\u8499\u592a\u5947 \ubabd\ud0c0\uc8fc",
        "\u96a7\u9053 \ud130\ub110",
        "\u6f58\u591a\u62c9 \ud310\ub3c4\ub77c"
    ],
    "male": "\u7537",
    "xingzuo": "\u5904\u5973\u5ea7",
    "birth": "1969-09-14",
    "area": "not found",
    "zhiye": [
        "\u6f14\u5458"
    ],
    "moreName": [
        "\u5218\u80dc\u7766",
        "\u67f3\u627f\u7a46"
    ],
    "family": [],
    "intro": "\n            \u3000\u3000\n    ",
    "hezuo": [
        [
            "\u5b8b\u6c38\u5f70 Young-chang Song",
            1
        ],
        [
            "\u88f4\u6597\u5a1c Doona Bae",
            1
        ],
        [
            "\u5434\u7199\u4fca Hee-joon Oh",
            1
        ],
        [
            "\u6734\u8d6b\u6743 Hyuk-kwon Park",
            1
        ],
        [
            "\u674e\u4fca\u8d6b Joon-Hyuk Lee",
            1
        ],
        [
            "\u91d1\u660e\u6c11 Myeong-min Kim",
            1
        ],
        [
            "\u6734\u54f2\u6c11 Cheol-min Park",
            1
        ],
        [
            "\u4e25\u6b63\u5316 Jeong-hwa Eom",
            1
        ],
        [
            "\u5357\u5fd7\u94c9 Ji-hyeon Nam",
            1
        ],
        [
            "\u91d1\u5357\u4f76 Nam-gil Kim",
            1
        ]
    ]
}