{
    "name": "\u52b3\u4f26\u00b7\u65af\u5361\u6cd5\u8389\u5a05 Lorene Scafaria",
    "movies": [
        "\u5f57\u661f\u6765\u7684\u90a3\u4e00\u591c Coherence"
    ],
    "male": "\u5973",
    "xingzuo": "\u91d1\u725b\u5ea7",
    "birth": "1978-05-01",
    "area": "\u7f8e\u56fd.\u65b0\u6cfd\u897f\u5dde,\u5b5f\u83ab\u65af\u90e1,\u542b\u5fb7\u9547",
    "zhiye": [
        "\u7f16\u5267",
        "\u5bfc\u6f14",
        "\u6f14\u5458"
    ],
    "moreName": [],
    "family": [
        "\u4e9a\u5f53\u00b7\u5e03\u7f57\u8fea(\u524d\u7537\u53cb)"
    ],
    "intro": "\n            \u3000\u3000\u7f8e\u56fd\u5bfc\u6f14\u3001\u7f16\u5267\uff0c2012\u5e74\u6267\u5bfc\u7535\u5f71\u5904\u5973\u4f5c\u300a\u672b\u4e16\u60c5\u7f18\u300b\u30022015\u5e74\u6267\u5bfc\u7684\u7b2c\u4e8c\u90e8\u7535\u5f71\u300a\u8001\u5988\u64cd\u788e\u5fc3\u300b\u83b7\u5f97\u597d\u8bc4\u3002\n    ",
    "hezuo": [
        [
            "\u83ab\u745e\u00b7\u53f2\u7279\u6797 Maury Sterling",
            1
        ],
        [
            "\u96e8\u679c\u00b7\u963f\u59c6\u65af\u7279\u6717 Hugo Armstrong",
            1
        ],
        [
            "\u4f0a\u4e3d\u838e\u767d\u00b7\u683c\u745e\u65af Elizabeth Gracen",
            1
        ],
        [
            "\u52b3\u4f26\u00b7\u9a6c\u8d6b Lauren Maher",
            1
        ],
        [
            "\u5c3c\u53e4\u62c9\u65af\u00b7\u5e03\u5170\u767b Nicholas Brendon",
            1
        ],
        [
            "\u4e9a\u5386\u514b\u65af\u00b7\u9a6c\u52aa\u5409\u5b89 Alex Manugian",
            1
        ],
        [
            "\u827e\u7c73\u4e3d\u00b7\u82ad\u5c14\u591a\u5c3c Emily Baldoni",
            1
        ],
        [
            "\u8096\u592e Yang Xiao",
            0
        ],
        [
            "\u6770\u514b\u00b7\u6606\u5361 Jake Cuenca",
            0
        ],
        [
            "\u8302\u6587\u00b7\u9053\u683c\u62c9\u65af Melvyn Douglas",
            0
        ]
    ]
}