{
    "name": "\u5361\u5c14\u00b7\u5384\u672c Karl Urban",
    "movies": [
        "\u661f\u9645\u8ff7\u822a2\uff1a\u6697\u9ed1\u65e0\u754c Star Trek Into Darkness",
        "\u661f\u9645\u8ff7\u822a Star Trek",
        "\u96f7\u795e3\uff1a\u8bf8\u795e\u9ec4\u660f Thor: Ragnarok",
        "\u661f\u9645\u8ff7\u822a3\uff1a\u8d85\u8d8a\u661f\u8fb0 Star Trek Beyond",
        "\u8c0d\u5f71\u91cd\u91cd2 The Bourne Supremacy"
    ],
    "male": "\u7537",
    "xingzuo": "\u53cc\u5b50\u5ea7",
    "birth": "1972-06-07",
    "area": "\u65b0\u897f\u5170,\u60e0\u7075\u987f",
    "zhiye": [
        "\u6f14\u5458",
        "\u914d\u97f3"
    ],
    "moreName": [],
    "family": [
        "Natalie Wihongi\uff08\u524d\u59bb\uff09"
    ],
    "intro": "\n            \u3000\u3000\u5361\u5c14-\u6d77\u5179\u00b7\u5384\u672c (Karl-Heinz Urban\uff0c1972\u5e746\u67087\u65e5\uff0d)\uff0c\u65b0\u897f\u5170\u7c4d\u7684\u7537\u6f14\u5458\u3002\u4ee3\u8868\u4f5c\u4e3a\u300a\u9b54\u6212\u4e09\u90e8\u66f2\u300b\u7b2c\u4e8c\u90e8\u4ee5\u53ca\u7b2c\u4e09\u90e8\u7684\u4f0a\u6b27\u58a8\u3001\u300a\u795e\u9b3c\u8ba4\u8bc1\uff1a\u795e\u9b3c\u7591\u4e91\u300b\u4e2d\u7684Kirill\u3001\u300a\u6bc1\u706d\u6218\u58eb\u300b\uff0c\u4ee5\u53ca\u300a\u8d85\u4e16\u7eaa\u6218\u8b66\u300b\u4e2d\u7684\u74e6\u53ef\u3002\n    ",
    "hezuo": [
        [
            "\u624e\u514b\u745e\u00b7\u6606\u56fe Zachary Quinto",
            3
        ],
        [
            "\u514b\u91cc\u65af\u00b7\u6d3e\u6069 Chris Pine",
            3
        ],
        [
            "\u897f\u8499\u00b7\u4f69\u5409 Simon Pegg",
            3
        ],
        [
            "\u4f50\u4f0a\u00b7\u7d22\u5c14\u8fbe\u5a1c Zoe Saldana",
            3
        ],
        [
            "\u5b89\u4e1c\u00b7\u53f6\u5229\u94a6 Anton Yelchin",
            3
        ],
        [
            "\u7ea6\u7ff0\u00b7\u8d75 John Cho",
            3
        ],
        [
            "\u4f0a\u5fb7\u91cc\u65af\u00b7\u827e\u5c14\u5df4 Idris Elba",
            2
        ],
        [
            "\u672c\u5c3c\u8fea\u514b\u7279\u00b7\u5eb7\u4f2f\u5df4\u5947 Benedict Cumberbatch",
            2
        ],
        [
            "\u5e03\u9c81\u65af\u00b7\u683c\u6797\u4f0d\u5fb7 Bruce Greenwood",
            2
        ],
        [
            "\u743c\u00b7\u827e\u4f26 Joan Allen",
            1
        ]
    ]
}