{
    "name": "\u53f8\u5f92\u9882\u66e6 Hayden Szeto",
    "movies": [
        "\u771f\u5fc3\u8bdd\u5927\u5192\u9669 Truth or Dare"
    ],
    "male": "\u7537",
    "xingzuo": "\u5904\u5973\u5ea7",
    "birth": "1985-09-11",
    "area": "\u52a0\u62ff\u5927,\u6e29\u54e5\u534e,\u4e0d\u5217\u98a0\u54e5\u4f26\u6bd4\u4e9a",
    "zhiye": [
        "\u6f14\u5458"
    ],
    "moreName": [
        "\u6d77\u767b\u00b7\u53f8\u5f92"
    ],
    "family": [
        "\u53f8\u5f92\u5947\uff08\u7956\u7236\uff09",
        "\u53f8\u5f92\u4e43\u949f\uff08\u7236\uff09"
    ],
    "intro": "\n\u3000\u3000Studied at the New York Film Academy.\u3000\u3000Parents are from Hong Kong.\u3000\u3000Studied at the Ivana Chubbuck Studio in Los Angeles.\u3000\u3000Grandson of famous Chinese painter, Kei Szeto.\u3000\u3000His Chinese name means \"Sunrise\".\u3000\u3000Both his grandfather, Kei Szeto and father, Nigel Szeto are famous painters in China.\u3000\u3000Has a family lineage of famous artists including painters, sculptors and poets.\u3000\u3000Speaks Cantonese and Mandarin Chinese.\u3000\u3000Born a...(\u5c55\u5f00\u5168\u90e8)\n\u3000\u3000Studied at the New York Film Academy.\u3000\u3000Parents are from Hong Kong.\u3000\u3000Studied at the Ivana Chubbuck Studio in Los Angeles.\u3000\u3000Grandson of famous Chinese painter, Kei Szeto.\u3000\u3000His Chinese name means \"Sunrise\".\u3000\u3000Both his grandfather, Kei Szeto and father, Nigel Szeto are famous painters in China.\u3000\u3000Has a family lineage of famous artists including painters, sculptors and poets.\u3000\u3000Speaks Cantonese and Mandarin Chinese.\u3000\u3000Born and raised in Vancouver, British Columbia.\u3000\u3000Has Canadian and Hong Kong citizenship.\u3000\u3000Has done major commercials for Walmart, Adidas, Nike, Coca Cola, Honda and Microsoft.\n",
    "hezuo": [
        [
            "\u7d22\u83f2\u5a05\u00b7\u963f\u91cc Sophia Ali",
            1
        ],
        [
            "\u9732\u897f\u00b7\u6d77\u5c14 Lucy Hale",
            1
        ],
        [
            "\u8bfa\u5170\u00b7\u6770\u62c9\u5fb7\u00b7\u51af\u514b Nolan Gerard Funk",
            1
        ],
        [
            "\u5965\u7f57\u62c9\u00b7\u4f69\u91cc\u8bfa Aurora Perrineau",
            1
        ],
        [
            "\u5170\u767b\u00b7\u83b1\u4f2f\u9686 Landon Liboiron",
            1
        ],
        [
            "\u5c71\u59c6\u00b7\u52d2\u7eb3 Sam Lerner",
            1
        ],
        [
            "\u7ef4\u5965\u83b1\u7279\u00b7\u6bd4\u6069 Violett Beane",
            1
        ],
        [
            "\u6cf0\u52d2\u00b7\u73c0\u897f Tyler Posey",
            1
        ],
        [
            "\u6c64\u59c6\u00b7\u8521 Tom Choi",
            1
        ],
        [
            "\u8096\u592e Yang Xiao",
            0
        ]
    ]
}