{
    "name": "\u54c8\u9c81\u514b\u00b7\u6bd4\u5c14\u6839\u7eb3\u5c14 Haluk Bilginer",
    "movies": [
        "\u6708\u5149\u5149\u5fc3\u614c\u614c Halloween"
    ],
    "male": "\u7537",
    "xingzuo": "\u53cc\u5b50\u5ea7",
    "birth": "1954-06-05",
    "area": "\u571f\u8033\u5176,\u4f0a\u5179\u5bc6\u5c14",
    "zhiye": [
        "\u6f14\u5458",
        "\u914d\u97f3"
    ],
    "moreName": [
        "\u54c8\u7559\u514b\u00b7\u6bd4\u5c14\u5409\u5185\u5c14"
    ],
    "family": [],
    "intro": "\n            \u3000\u3000\n    ",
    "hezuo": [
        [
            "\u5b89\u8fea\u00b7\u9a6c\u8482\u5207\u514b Andi Matichak",
            1
        ],
        [
            "\u6258\u6bd4\u00b7\u54c8\u65af Toby Huss",
            1
        ],
        [
            "\u6770\u7c73\u00b7\u674e\u00b7\u67ef\u8482\u65af Jamie Lee Curtis",
            1
        ],
        [
            "\u5a01\u5c14\u00b7\u5e15\u987f Will Patton",
            1
        ],
        [
            "\u91cc\u5b89\u00b7\u91cc\u65af Rhian Rees",
            1
        ],
        [
            "\u6770\u4f5b\u900a\u00b7\u8c6a\u5c14 Jefferson Hall",
            1
        ],
        [
            "\u6731\u8fea\u00b7\u683c\u96f7\u5c14 Judy Greer",
            1
        ],
        [
            "\u8a79\u59c6\u65af\u00b7\u88d8\u5fb7\u00b7\u67ef\u7279\u5c3c James Jude Courtney",
            1
        ],
        [
            "\u5c3c\u514b\u00b7\u5361\u65af\u7279\u5c14 Nick Castle",
            1
        ],
        [
            "\u8096\u592e Yang Xiao",
            0
        ]
    ]
}