{
    "name": "\u591a\u7c73\u5c3c\u514b\u00b7\u4f2f\u5409\u65af Dominic Burgess",
    "movies": [
        "\u6050\u6016\u5927\u5988 Ma"
    ],
    "male": "\u7537",
    "xingzuo": "\u72ee\u5b50\u5ea7",
    "birth": "1982-07-29",
    "area": "\u82f1\u56fd,\u7279\u4f26\u7279\u6cb3\u7554\u65af\u6258\u514b",
    "zhiye": [
        "\u6f14\u5458"
    ],
    "moreName": [],
    "family": [],
    "intro": "\n            \u3000\u3000\n    ",
    "hezuo": [
        [
            "\u6731\u4e3d\u53f6\u7279\u00b7\u5218\u6613\u65af Juliette Lewis",
            1
        ],
        [
            "\u6234\u5b89\u5a1c\u00b7\u897f\u5c14\u5f17\u65af Diana Silvers",
            1
        ],
        [
            "\u5362\u514b\u00b7\u4f0a\u4e07\u65af Luke Evans",
            1
        ],
        [
            "\u5965\u514b\u5854\u7ef4\u4e9a\u00b7\u65af\u5bbe\u745f Octavia Spencer",
            1
        ],
        [
            "\u827e\u8389\u68ee\u00b7\u73cd\u59ae Allison Janney",
            1
        ],
        [
            "\u7ef4\u514b\u6258\u00b7\u7279\u5e73 Victor Turpin",
            1
        ],
        [
            "\u7c73\u897f\u00b7\u6d3e\u52d2 Missi Pyle",
            1
        ],
        [
            "\u9ea6\u514b\u5229\u00b7\u7c73\u52d2 McKaley Miller",
            1
        ],
        [
            "\u4e39\u7279\u00b7\u5e03\u6717 Dante Brown",
            1
        ],
        [
            "\u8096\u592e Yang Xiao",
            0
        ]
    ]
}