{
    "name": "\u5f20\u5353\u6960 Brandon Chang",
    "movies": [
        "\u98de\u9e70",
        "\u5929\u8109\u4f20\u5947"
    ],
    "male": "\u7537",
    "xingzuo": "\u6469\u7faf\u5ea7",
    "birth": "1982-12-28",
    "area": "\u52a0\u62ff\u5927,\u591a\u4f26\u591a",
    "zhiye": [
        "\u6f14\u5458"
    ],
    "moreName": [],
    "family": [],
    "intro": "\n            \u3000\u3000\u4e3a\u300a\u521b\u65b0\u827a\u4eba\u7ecf\u7eaa\u516c\u53f8CAA \u300b\u65d7\u4e0b\u6f14\u5458\u3002\u66fe\u62cd\u8fc7\u7535\u5f71\u300a\u5929\u8109\u4f20\u5947\u300b\u3001\u300a\u98de\u9e70\u300b\uff0c\u4ee5\u53ca\u5fae\u7535\u5f71\u300a\u5341\u79d2\u7684\u51b2\u52a8\u300b\u7b49\u3002\u9664\u4e86\u5f53\u6f14\u5458\uff0c\u4ea6\u66fe\u521b\u7acb\u7f8e\u56fd\u77e5\u540d\u6f6e\u6d41\u54c1\u724cGreedy Genius\uff0c\u5e76\u4e8e2009\u5e74\u8363\u83b7\u300a\u5546\u4e1a\u5468\u520a\u300b\uff08Business Week Magazine\uff09\u8bc4\u9009\u4e3a\u5e74\u5ea6\u4e9a\u6d3225\u4f4d\u6700\u5e74\u8f7b\u4f01\u4e1a\u5bb6\u4e4b\u4e00\u3002\u76ee\u524d\u62c5\u4efb\u56fd\u9645\u5f71\u661f\u300a\u8d3e\u767b\u00b7\u53f2\u5bc6\u65af \u300bJadenSmith \u6240\u521b\u7acb\u4e4b\u54c1\u724cMSFTSrep\u4e9a\u6d32\u533a\u4ee3\u8868\uff0c\u5e76\u4e14\u53e6\u4e0e\u77e5\u540d\u6b4c\u624b\u6797\u4fca\u6770\u5408\u4f19\u53ca\u5171\u540c\u7ecf\u8425\u4e9a\u6d32\u6f6e\u6d41\u54c1\u724cSMG\u3002\n    ",
    "hezuo": [
        [
            "\u6768\u7d2b\u743c Michelle Yeoh",
            2
        ],
        [
            "\u6234\u6069\u00b7\u5e93\u514b Dane Cook",
            1
        ],
        [
            "\u5e03\u5170\u767b\u00b7\u96f7\u4e9a Brandon Rhea",
            1
        ],
        [
            "\u738b\u5b87\u5a55 Margaret Wang",
            1
        ],
        [
            "\u9648\u5927\u660e Daming Chen",
            1
        ],
        [
            "\u672c\u00b7\u5353\u522b\u6797 Ben Chaplin",
            1
        ],
        [
            "\u66fe\u6c5f Kenneth Tsang",
            1
        ],
        [
            "\u7406\u67e5\u5fb7\u00b7\u52b3\u65af\u4f2f\u683c Richard Roxburgh",
            1
        ],
        [
            "\u4efb\u8d24\u9f50 Richie Jen",
            1
        ],
        [
            "\u9c81\u514b\u00b7\u9ad8\u65af Luke Goss",
            1
        ]
    ]
}