{
    "name": "\u5f20\u9ed8 Mo Zhang",
    "movies": [
        "\u8ba9\u5b50\u5f39\u98de"
    ],
    "male": "\u7537",
    "xingzuo": "\u72ee\u5b50\u5ea7",
    "birth": "1982-07-28",
    "area": "\u4e2d\u56fd,\u56db\u5ddd,\u6210\u90fd",
    "zhiye": [
        "\u6f14\u5458",
        "\u5bfc\u6f14",
        "\u526f\u5bfc\u6f14"
    ],
    "moreName": [],
    "family": [
        "\u5f20\u56fd\u7acb(\u7236\u4eb2)",
        "\u7f57\u79c0\u6625(\u6bcd)"
    ],
    "intro": "\n            \u3000\u3000\u5f20\u9ed8\uff0c\u4e2d\u56fd\u5185\u5730\u7537\u6f14\u5458\uff0c\u5df2\u51fa\u6f14\u591a\u90e8\u7535\u89c6\u8fde\u7eed\u5267\u548c\u7535\u5f71\u30022003\u5e74\u56e0\u4e3a\u6253\u4eba\u4e8b\u4ef6\u9677\u5165\u98ce\u53e3\u6d6a\u5c16\u30022012\u5e741\u670831\u65e5\u665a\uff0c\u5317\u4eac\u987a\u4e49\u8b66\u65b9\u8bc1\u5b9e\uff0c\u5f20\u9ed8\u56e0\u6d89\u5acc\u5438\u6bd2\u88ab\u5e26\u8d70\u3002\u4fdd\u6301\u7f04\u9ed8\u7684\u5f20\u56fd\u7acb\u6700\u7ec8\u57282\u67081\u65e5\u51cc\u6668\u53d1\u5e03\u58f0\u660e\uff0c\u627f\u8ba4\u4e86\u513f\u5b50\u5f20\u9ed8\u5438\u98df\u5927\u9ebb\u88ab\u5317\u4eac\u8b66\u65b9\u62d8\u7559\u3002\u5f20\u56fd\u7acb\u672c\u4eba\u79f0\u5bf9\u5317\u4eac\u8b66\u65b9\u7684\u884c\u4e3a\u8868\u793a\u575a\u51b3\u652f\u6301\u30022\u670814\u65e5\u51cc\u6668\uff0c\u5f20\u9ed8\u884c\u653f\u62d8\u7559\u671f\u6ee1\u3002\u83b7\u91ca\u540e\uff0c\u4ed6\u7b2c\u4e00\u65f6\u95f4\u8054\u7edc\u5e76\u59d4\u6258\u534e\u8c0a\u5144\u5f1f\u7ecf\u7eaa\u516c\u53f8\uff0c\u53d1\u8868\u9053\u6b49\u58f0\u660e\u5411\u516c\u4f17\u81f4\u6b49\u3002\n    ",
    "hezuo": [
        [
            "\u9648\u5764 Kun Chen",
            1
        ],
        [
            "\u59dc\u6b66 Wu Jiang",
            1
        ],
        [
            "\u59da\u6a79 Lu Yao",
            1
        ],
        [
            "\u5218\u5609\u73b2 Carina Lau",
            1
        ],
        [
            "\u5468\u97f5 Yun Zhou",
            1
        ],
        [
            "\u845b\u4f18 You Ge",
            1
        ],
        [
            "\u59dc\u6587 Wen Jiang",
            1
        ],
        [
            "\u5468\u6da6\u53d1 Yun-Fat Chow",
            1
        ],
        [
            "\u5ed6\u51e1 Fan Liao",
            1
        ],
        [
            "\u8096\u592e Yang Xiao",
            0
        ]
    ]
}