{
    "name": "\u624e\u5207\u91cc\u00b7\u6cf0\u00b7\u5e03\u83b1\u6069 Zachery Ty Bryan",
    "movies": [
        "\u901f\u5ea6\u4e0e\u6fc0\u60c53\uff1a\u4e1c\u4eac\u6f02\u79fb The Fast and the Furious: Tokyo Drift"
    ],
    "male": "\u7537",
    "xingzuo": "\u5929\u79e4\u5ea7",
    "birth": "1981-10-09",
    "area": "\u7f8e\u56fd,\u79d1\u7f57\u62c9\u591a\u5dde,\u5965\u7f57\u62c9",
    "zhiye": [
        "\u6f14\u5458",
        "\u5236\u7247\u4eba"
    ],
    "moreName": [],
    "family": [],
    "intro": "\n            \u3000\u3000\n    ",
    "hezuo": [
        [
            "\u5317\u5ddd\u666f\u5b50 Keiko Kitagawa",
            1
        ],
        [
            "\u5b9d\u5a03 Bow Wow",
            1
        ],
        [
            "\u7eb3\u5854\u8389\u00b7\u51ef\u5229 Nathalie Kelley",
            1
        ],
        [
            "\u5343\u53f6\u771f\u4e00 Sonny Chiba",
            1
        ],
        [
            "\u5362\u5361\u65af\u00b7\u5e03\u83b1\u514b Lucas Black",
            1
        ],
        [
            "\u59dc\u6210\u9550 Sung Kang",
            1
        ],
        [
            "\u5e03\u83b1\u6069\u00b7\u53e4\u5fb7\u66fc Brian Goodman",
            1
        ],
        [
            "\u59bb\u592b\u6728\u806a Satoshi Tsumabuki",
            1
        ],
        [
            "\u5e03\u83b1\u6069\u00b7\u6cf0 Brian Tee",
            1
        ],
        [
            "\u8096\u592e Yang Xiao",
            0
        ]
    ]
}