{
    "name": "\u6770\u5f17\u91cc\u00b7\u5e03\u83b1\u514b Geoffrey Blake",
    "movies": [
        "\u8d85\u65f6\u7a7a\u63a5\u89e6 Contact"
    ],
    "male": "\u7537",
    "xingzuo": "\u72ee\u5b50\u5ea7",
    "birth": "1962-08-20",
    "area": "\u7f8e\u56fd,\u9a6c\u91cc\u5170",
    "zhiye": [
        "\u6f14\u5458",
        "\u914d\u97f3"
    ],
    "moreName": [],
    "family": [],
    "intro": "\n            \u3000\u3000\n    ",
    "hezuo": [
        [
            "\u7ea6\u7ff0\u00b7\u8d6b\u7279 John Hurt",
            1
        ],
        [
            "\u6731\u8fea\u00b7\u798f\u65af\u7279 Jodie Foster",
            1
        ],
        [
            "\u9a6c\u4fee\u00b7\u9ea6\u5eb7\u7eb3 Matthew McConaughey",
            1
        ],
        [
            "\u5927\u536b\u00b7\u6469\u65af David Morse",
            1
        ],
        [
            "\u5a01\u5ec9\u00b7\u83f2\u514b\u7eb3 William Fichtner",
            1
        ],
        [
            "\u8a79\u59c6\u65af\u00b7\u4f0d\u5179 James Woods",
            1
        ],
        [
            "\u5b89\u5409\u62c9\u00b7\u8d1d\u585e\u7279 Angela Bassett",
            1
        ],
        [
            "\u5409\u5a1c\u00b7\u9a6c\u9686 Jena Malone",
            1
        ],
        [
            "\u8096\u592e Yang Xiao",
            0
        ],
        [
            "\u6770\u514b\u00b7\u6606\u5361 Jake Cuenca",
            0
        ]
    ]
}