{
    "name": "\u6797\u66f4\u65b0 Gengxin Lin",
    "movies": [
        "\u667a\u53d6\u5a01\u864e\u5c71",
        "\u75de\u5b50\u82f1\u96c42\uff1a\u9ece\u660e\u5347\u8d77 \u75de\u5b50\u82f1\u96c42\uff1a\u9ece\u660e\u518d\u8d77",
        "\u72c4\u4ec1\u6770\u4e4b\u795e\u90fd\u9f99\u738b",
        "\u4e09\u5c11\u7237\u7684\u5251"
    ],
    "male": "\u7537",
    "xingzuo": "\u6c34\u74f6\u5ea7",
    "birth": "1988-02-13",
    "area": "\u4e2d\u56fd,\u8fbd\u5b81,\u6c88\u9633",
    "zhiye": [
        "\u6f14\u5458",
        "\u914d\u97f3",
        "\u4e3b\u6301\u4eba"
    ],
    "moreName": [
        "\u5c0f\u65b0(\u6635\u79f0)"
    ],
    "family": [],
    "intro": "\n            \u3000\u3000\u6797\u66f4\u65b0\uff0c\u4e2d\u56fd\u5185\u5730\u6f14\u5458\uff0c1988\u5e742\u670813\u65e5\u51fa\u751f\uff0c\u6bd5\u4e1a\u4e8e\u4e0a\u6d77\u620f\u5267\u5b66\u9662\uff0c\u66fe\u51fa\u6f14\u300a\u79d8\u679c\u300b\u300a\u56e0\u4e3a\u7231\u4e4b\u8bf4\u51fa\u4f60\u7684\u79d8\u5bc6\u300b\uff08\u7f51\u7edc\u5267\uff09\uff0c\u5728\u300a\u6b65\u6b65\u60ca\u5fc3\u300b\u4e2d\u9970\u6f14\u5341\u56db\u963f\u54e5\uff0c\u662f\u8212\u857e\u6d17\u53d1\u6c34\u5e7f\u544a\u300a\u6211\u7684\u5973\u670b\u53cb\u300b\u2014\u2014\u7cfb\u5217\u7537\u4e3b\u89d2\u3002\n    ",
    "hezuo": [
        [
            "\u9a6c\u4eac\u4eac Jingjing Ma",
            2
        ],
        [
            "\u8d75\u53c8\u5ef7 Mark Chao",
            2
        ],
        [
            "\u76db\u9274 Chien Sheng",
            1
        ],
        [
            "\u5434\u5143\u4fca Yuan-chun Wu",
            1
        ],
        [
            "\u5173\u9896 Terri Kwan",
            1
        ],
        [
            "\u848b\u68a6\u5a55 Mengjie Jiang",
            1
        ],
        [
            "\u9c8d\u8d77\u9759 Hee Ching Paw",
            1
        ],
        [
            "\u6768\u9896 Angelababy",
            1
        ],
        [
            "\u987e\u51a0\u5fe0 Kuan-chung Ku",
            1
        ],
        [
            "\u8521\u5cb3\u52cb Yueh-Hsun Tsai",
            1
        ]
    ]
}