{
    "name": "\u82cf\u83f2\u00b7\u7279\u7eb3 Sophie Turner",
    "movies": [
        "X\u6218\u8b66\uff1a\u5929\u542f X-Men: Apocalypse",
        "X\u6218\u8b66\uff1a\u9ed1\u51e4\u51f0 Dark Phoenix"
    ],
    "male": "\u5973",
    "xingzuo": "\u53cc\u9c7c\u5ea7",
    "birth": "1996-02-21",
    "area": "\u82f1\u56fd,\u82f1\u683c\u5170,\u5317\u5b89\u666e\u6566",
    "zhiye": [
        "\u6f14\u5458",
        "\u914d\u97f3"
    ],
    "moreName": [
        "\u7d22\u83f2\u00b7\u7279\u7eb3"
    ],
    "family": [
        "Joe Jonas(\u592b)"
    ],
    "intro": "\n            \u3000\u30001996\u5e742\u6708 21\u65e5\u51fa\u751f\u5728\u82f1\u56fd\u5317\u5b89\u666e\u6566\uff08Northampton\uff09\uff0c2\u5c81\u65f6\u5bb6\u91cc\u642c\u5230\u534e\u5a01\uff08Warwick\uff09\uff0c\u5728\u534e\u5a01\u8457\u540d\u7684Playbox Theatre\u5b66\u4e60\u620f\u5267\u3002\u3000\u3000\u5c0f\u8bf4\u300a\u51b0\u4e0e\u706b\u4e4b\u6b4c\u300b\u6539\u7f16\u7684HBO\u7535\u89c6\u5267\u300aGame of Thrones\u300b\u4e2d\u9970\u6f14\u73ca\u838e\u53f2\u5854\u514b\uff08Sansa Stark\uff09\u3002\u8fd9\u4e5f\u662f\u5979\u7b2c\u4e00\u4e2a\u5f71\u89c6\u4f5c\u54c1\u3002\n    ",
    "hezuo": [
        [
            "\u57c3\u6587\u00b7\u5f7c\u5f97\u65af Evan Peters",
            2
        ],
        [
            "\u8fc8\u514b\u5c14\u00b7\u6cd5\u65af\u5bbe\u5fb7 Michael Fassbender",
            2
        ],
        [
            "\u5c3c\u53e4\u62c9\u65af\u00b7\u970d\u5c14\u7279 Nicholas Hoult",
            2
        ],
        [
            "\u8a79\u59ae\u5f17\u00b7\u52b3\u4f26\u65af Jennifer Lawrence",
            2
        ],
        [
            "\u8a79\u59c6\u65af\u00b7\u9ea6\u5361\u6c83\u4f0a James McAvoy",
            2
        ],
        [
            "\u7f57\u4e1d\u00b7\u4f2f\u6069 Rose Byrne",
            1
        ],
        [
            "\u6cf0\u4f0a\u00b7\u8c22\u91cc\u4e39 Tye Sheridan",
            1
        ],
        [
            "\u4f11\u00b7\u6770\u514b\u66fc Hugh Jackman",
            1
        ],
        [
            "\u4e9a\u5386\u5c71\u5fb7\u62c9\u00b7\u5e0c\u666e Alexandra Shipp",
            1
        ],
        [
            "\u5965\u65af\u5361\u00b7\u4f0a\u8428\u514b Oscar Isaac",
            1
        ]
    ]
}