{
    "name": "\u8881\u6587\u5eb7 Wenkang Yuan",
    "movies": [
        "\u96c6\u7ed3\u53f7",
        "\u66b4\u88c2\u65e0\u58f0",
        "\u627e\u5230\u4f60",
        "\u4eb2\u7231\u7684\u65b0\u5e74\u597d"
    ],
    "male": "\u7537",
    "xingzuo": "\u72ee\u5b50\u5ea7",
    "birth": "1980-07-23",
    "area": "\u4e2d\u56fd,\u4e0a\u6d77",
    "zhiye": [
        "\u6f14\u5458"
    ],
    "moreName": [],
    "family": [],
    "intro": "\n            \u3000\u3000\u4f5c\u4e3a\u534e\u8c0a\u5144\u5f1f\u529b\u6367\u7684\u5e74\u5ea6\u9ed1\u9a6c\u8881\u6587\u5eb7\uff0c\u7ee7\u9646\u7eed\u53c2\u6f14\u51af\u5c0f\u521a\u8d3a\u5c81\u6218\u4e89\u5927\u7247\u7535\u5f71\u300a\u96c6\u7ed3\u53f7\u300b\uff0c\u4e2d\u97e9\u5408\u4f5c\u5076\u50cf\u5267\u300a\u604b\u7231\u5175\u6cd5\u300b\u4e4b\u540e\uff0c\u65e5\u524d\u66f4\u662f\u4ee5\u201c\u6700\u540e\u66dd\u5149\u7684\u4e2d\u56fd\u9762\u5b54\u201d\u59ff\u6001\u5165\u7ec4\u7531\u534e\u8c0a\u5144\u5f1f\u548c\u5fb7\u56fd\u8c6a\u592b\u66fc\u548c\u4f5b\u683c\u65af\u5a31\u4e50\u516c\u53f8\u5171\u540c\u6295\u8d44\u7684\u7535\u5f71\u300a\u7ea6\u7ff0\u00b7\u62c9\u8d1d\u300b\uff0c\u53ef\u8c13\u661f\u9014\u65e0\u91cf\u3002\n    ",
    "hezuo": [
        [
            "\u738b\u6893\u5c18 Zichen Wang",
            2
        ],
        [
            "\u59dc\u6b66 Wu Jiang",
            1
        ],
        [
            "\u9f50\u6b22 Huan Qi",
            1
        ],
        [
            "\u9093\u8d85 Chao Deng",
            1
        ],
        [
            "\u674e\u5efa\u4e49 Jianyi Li",
            1
        ],
        [
            "\u4f0a\u5929\u9534 Tiankai YIn",
            1
        ],
        [
            "\u738b\u5b9d\u5f3a Baoqiang Wang",
            1
        ],
        [
            "\u5b89\u7425 Hu An",
            1
        ],
        [
            "\u5434\u660a\u5bb8 Haochen Wu",
            1
        ],
        [
            "\u5218\u7545 Chang Liu",
            1
        ]
    ]
}