{
    "name": "\u9edb\u5b89\u00b7\u8d1d\u514b Diane Baker",
    "movies": [
        "\u738b\u724c\u7279\u6d3e\u5458 The Cable Guy",
        "\u8273\u8d3c Marnie"
    ],
    "male": "\u5973",
    "xingzuo": "\u53cc\u9c7c\u5ea7",
    "birth": "1938-02-25",
    "area": "\u7f8e\u56fd,\u52a0\u5229\u798f\u5c3c\u4e9a\u5dde,\u597d\u83b1\u575e",
    "zhiye": [
        "\u6f14\u5458",
        "\u5236\u7247\u4eba",
        "\u914d\u97f3"
    ],
    "moreName": [],
    "family": [],
    "intro": "\n            \u3000\u3000Diane Carol Baker (born February 25, 1938) is an American actress and producer who has appeared in motion pictures and on television since 1959.\n    ",
    "hezuo": [
        [
            "\u8482\u6bd4\u00b7\u6d77\u5fb7\u8389 Tippi Hedren",
            1
        ],
        [
            "\u91d1\u00b7\u51ef\u745e Jim Carrey",
            1
        ],
        [
            "\u963f\u5170\u00b7\u7eb3\u76ae\u5c14 Alan Napier",
            1
        ],
        [
            "\u5b89\u8fea\u00b7\u8fea\u514b Andy Dick",
            1
        ],
        [
            "\u8def\u6613\u838e\u00b7\u5170\u745f\u59c6 Louise Latham",
            1
        ],
        [
            "\u9c8d\u52c3\u00b7\u65af\u5a01\u5c3c Bob Sweeney",
            1
        ],
        [
            "\u4ea8\u5229\u00b7\u8d1d\u514b\u66fc Henry Beckman",
            1
        ],
        [
            "\u57c3\u91cc\u514b\u00b7\u7f57\u4f2f\u8328 Eric Roberts",
            1
        ],
        [
            "\u83b1\u65af\u5229\u00b7\u66fc\u6069 Leslie Mann",
            1
        ],
        [
            "\u8a79\u59ae\u5b89\u00b7\u52a0\u7f57\u6cd5\u6d1b Janeane Garofalo",
            1
        ]
    ]
}