{
    "director": "\u76d6\u5c14\u00b7\u66fc\u5e93\u7d22",
    "bianju": "W\u00b7\u5e03\u9c81\u65af\u00b7\u5361\u6885\u4f26 / \u739b\u96c5\u00b7\u798f\u5e03\u65af / \u51ef\u745f\u7433\u00b7\u8fc8\u514b / \u534e\u83b1\u58eb\u00b7\u6c83\u6d1b\u8fbe\u65af\u57fa",
    "length": "108\u5206\u949f",
    "lang": [
        "\u82f1\u8bed"
    ],
    "area": [
        "\u4e2d\u56fd\u5927\u9646",
        "\u5370\u5ea6",
        "\u4e2d\u56fd\u9999\u6e2f",
        "\u7f8e\u56fd"
    ],
    "select": [
        "\u5267\u60c5",
        "\u559c\u5267",
        "\u5bb6\u5ead"
    ],
    "name": "\u4e00\u6761\u72d7\u7684\u4f7f\u547d2 A Dog's Journey",
    "year": "2019",
    "intro": "  \u3000\u3000\u5c0f\u72d7\u8d1d\u5229\u5ef6\u7eed\u4f7f\u547d\uff0c\u5728\u4e3b\u4eba\u4f0a\u68ee\u7684\u5631\u6258\u4e0b\uff0c\u901a\u8fc7\u4e0d\u65ad\u7684\u751f\u547d\u8f6e\u56de\uff0c \u6267\u7740\u5b88\u62a4\u4f0a\u68ee\u7684\u5b59\u5973CJ\uff0c\u5c06\u4f0a\u68ee\u5bf9\u5b59\u5973\u7684\u7231\u4e0e\u966a\u4f34\uff0c\u5f53\u505a\u6700\u91cd\u8981\u7684 \u4f7f\u547d\u548c\u610f\u4e49\uff0c\u6700\u7ec8\u5e2e\u52a9CJ\u6536\u83b7\u5e78\u798f\uff0c\u518d\u6b21\u56de\u5230\u4e3b\u4eba\u4f0a\u68ee\u8eab\u8fb9\u3002  ",
    "average": "7.0",
    "averageNum": null,
    "comments": [
        "\u8fd9\u4e00\u5bb6\u4eba\u771f\u8d39\u72d7\u554a",
        "\u8ba4\u51fa\u5218\u5baa\u534e\u7684\u6211\uff0c\u6bd4\u8ba4\u51fa\u8d1d\u5229\u7684\u4f0a\u68ee\u8fd8\u9707\u60ca\ud83d\ude02",
        "\u7b54\u5e94\u6211 \u8d1d\u5229  \u4f60\u4e0b\u8f88\u5b50\u4e0d\u8981\u5728\u6295\u80ce\u6210\u72d7\u597d\u4e48  \u5c31\u7b97\u662f\u72d7\u4e5f\u4e0d\u8981\u53bb\u4ed6\u5bb6\u597d\u4e48",
        "\u6211\u7684\u4e16\u754c\u6709\u5f88\u591a\u4eba\uff0c\u800c\u4f60\u7684\u4e16\u754c\u53ea\u6709\u6211\u3002",
        "\u9019\u4e00\u6b21\u773c\u7736\u6cdb\u6dda\ud83d\ude2d \u62cd\u7684\u6bd41\u597d\npart of the journey is the end"
    ],
    "actors": [
        "\u4e39\u5c3c\u65af\u00b7\u594e\u5fb7 Dennis Quaid",
        "\u51ef\u745f\u7433\u00b7\u666e\u96f7\u65af\u79d1\u7279 Kathryn Prescott",
        "\u5218\u5baa\u534e Henry Lau",
        "\u739b\u683c\u00b7\u6d77\u6839\u67cf\u683c Marg Helgenberger",
        "\u8d1d\u8482\u00b7\u5409\u5c14\u5e73 Betty Gilpin",
        "\u4e54\u4ec0\u00b7\u52a0\u5fb7 Josh Gad",
        "\u827e\u6bd4\u00b7\u83b1\u5fb7\u00b7\u5f17\u7279\u68ee Abby Ryder Fortson",
        "\u6770\u514b\u00b7\u66fc\u5229 Jake Manley",
        "\u8fbe\u59ae\u57c3\u62c9\u00b7\u5df4\u535a\u8428 Daniela Barbosa",
        "\u9648\u7426\u70e8 Ian Chen"
    ]
}